scm_python_deploy_ium/lib/ium_deploy.py
scm_python_deploy_ium/tapps/deploy/gwt.py
scm_python_deploy_ium/tapps/deploy/ium.py
scm_python_deploy_ium/tapps/deploy/mvn.py
scm_python_deploy_ium/tapps/deploy/npm.py
scm_python_deploy_ium/tapps/deploy/snap.py
scm_python_deploy_ium/tapps/deploy/war.py
scm_python_deploy_ium-0.1.0.dist-info/METADATA
scm_python_deploy_ium-0.1.0.dist-info/WHEEL
scm_python_deploy_ium-0.1.0.dist-info/top_level.txt
scm_python_deploy_ium-0.1.0.dist-info/RECORD
